selectorlib/__init__.py
selectorlib/cli.py
selectorlib/formatter.py
selectorlib/selectorlib.py
selectorlib-0.16.0.dist-info/AUTHORS.rst
selectorlib-0.16.0.dist-info/LICENSE
selectorlib-0.16.0.dist-info/METADATA
selectorlib-0.16.0.dist-info/WHEEL
selectorlib-0.16.0.dist-info/entry_points.txt
selectorlib-0.16.0.dist-info/top_level.txt
selectorlib-0.16.0.dist-info/RECORD
