Metadata-Version: 1.1
Name: selectorlib
Version: 0.16.0
Summary: A library to read a YML file with Xpath or CSS Selectors and extract data from HTML pages using them
Home-page: https://github.com/scrapehero/selectorlib
Author: scrapehero
Author-email: pypi@scrapehero.com
License: MIT license
Keywords: selectorlib
Platform: UNKNOWN
Classifier: Development Status :: 2 - Pre-Alpha
Classifier: Intended Audience :: Developers
Classifier: License :: OSI Approved :: MIT License
Classifier: Natural Language :: English
Classifier: Programming Language :: Python :: 2
Classifier: Programming Language :: Python :: 2.7
Classifier: Programming Language :: Python :: 3
Classifier: Programming Language :: Python :: 3.4
Classifier: Programming Language :: Python :: 3.5
Classifier: Programming Language :: Python :: 3.6
Classifier: Programming Language :: Python :: 3.7
